[
    {
        "name": "Jose Terronez",
        "data": [
            {
                "date": "2017-09-20T00:00:00.00",
                "info": "OT201711490"
            },
            {
                "date": "2017-09-21T00:00:00.00",
                "info": "OT201711433"
            }
        ],
        "footer":[
            {
                "date": "2017-09-20T00:00:00.00",
                "contend": "N: 2 / D: 1"
            }
        ],
        "extra": {
            "pk_eTecnico": 5
        }
    }
]